{
  "extends": "tslint:all",
  "rules": {
    "align": false,
    "completed-docs": false,
    "member-access": false,
    "newline-before-return": false,
    "newline-per-chained-call": false,
    "no-any": false,
    "no-implicit-dependencies": [true, "dev"],
    "no-floating-promises": false,
    "no-submodule-imports": false,
    "no-unsafe-any": false,
    "no-use-before-declare": false,
    "only-arrow-functions": false,
    "quotemark": [
      true,
      "single"
    ],
    "strict-boolean-expressions": false,
    "trailing-comma": false,
    "typedef": false
  }
}
